collective.recipe.maildump-0.2.2-py2.7-nspkg.pth
collective/recipe/maildump/__init__.py
collective.recipe.maildump-0.2.2.dist-info/DESCRIPTION.rst
collective.recipe.maildump-0.2.2.dist-info/METADATA
collective.recipe.maildump-0.2.2.dist-info/RECORD
collective.recipe.maildump-0.2.2.dist-info/WHEEL
collective.recipe.maildump-0.2.2.dist-info/entry_points.txt
collective.recipe.maildump-0.2.2.dist-info/metadata.json
collective.recipe.maildump-0.2.2.dist-info/namespace_packages.txt
collective.recipe.maildump-0.2.2.dist-info/top_level.txt
