Metadata-Version: 2.0
Name: collective.recipe.maildump
Version: 0.2.2
Summary: Buildout recipe to install maildump
Home-page: https://github.com/collective/collective.recipe.maildump
Author: Noe Nieto
Author-email: nnieto@noenieto.com
License: BSD
Keywords: buildout recipe maildump
Platform: UNKNOWN
Classifier: Framework :: Buildout
Classifier: Intended Audience :: Developers
Classifier: Topic :: Software Development :: Build Tools
Classifier: Topic :: Software Development :: Libraries :: Python Modules
Classifier: License :: OSI Approved :: BSD License
Classifier: Development Status :: 4 - Beta
Classifier: Programming Language :: Python
Classifier: Programming Language :: Python :: 2.7
Classifier: Environment :: No Input/Output (Daemon)
Classifier: Environment :: Web Environment
Classifier: Intended Audience :: Developers
Classifier: Intended Audience :: System Administrators
Classifier: License :: OSI Approved :: MIT License
Classifier: Topic :: Communications :: Email
Classifier: Topic :: Software Development
Classifier: Topic :: System :: Networking
Classifier: Topic :: Utilities
Requires-Dist: setuptools
Requires-Dist: zc.buildout
Requires-Dist: zc.recipe.egg
